code/exp2/fsm/fsm_3.v
`timescale 1ns/1ps
module FSM_3
//---------------------<端口声明>---------------------------------------
(
input                   clk                 ,
input                   rst_n               ,
input      [1:0]        in                  ,
output reg [1:0]        out                 ,
output reg              out_vld
);
//---------------------<信号定义>---------------------------------------
reg  [3:0]              state_c             ;
reg  [3:0]              state_n             ;
//---------------------<状态机参数>-------------------------------------
localparam S0           = 4'b0001           ;
localparam S1           = 4'b0010           ;
localparam S2           = 4'b0100           ;
localparam S3           = 4'b1000           ;

//----------------------------------------------------------------------
//--   状态机第1段
//----------------------------------------------------------------------
always @(posedge clk or negedge rst_n)begin
    if(!rst_n)
        state_c <= S0;
    else
        state_c <= state_n;
end

//----------------------------------------------------------------------
//--   状态机第2段
//----------------------------------------------------------------------
always @(*)begin
    case(state_c)
        S0: begin
            if(in==1)
                state_n = S1;
            else if(in==2)
                state_n = S2;
            else
                state_n = state_c;
        end
        S1: begin
            if(in==1)
                state_n = S2;
            else if(in==2)
                state_n = S3;
            else
                state_n = state_c;
        end
        S2: begin
            if(in==1)
                state_n = S3;
            else if(in==2)
                state_n = S0;
            else
                state_n = state_c;
        end
        S3: begin
            if(in==1 || in==2)      // in != 0也行
                state_n = S0;
            else
                state_n = state_c;
        end
        default:state_n = S0;
    endcase
end

//----------------------------------------------------------------------
//--   状态机第3段
//----------------------------------------------------------------------
//找零钱
always @(posedge clk or negedge rst_n)begin
    if(!rst_n)
        out <= 0;
    else if(state_c==S3 && in==2)
        out <= 1;
    else
        out <= 0;
end

//输出脉动
always @(posedge clk or negedge rst_n)begin
    if(rst_n==1'b0)
        out_vld <= 0;
    else if((state_c==S2 && in==2) || (state_c==S3 && in!=0))
        out_vld <= 1;
    else
        out_vld <= 0;
end


endmodule

code/exp2/fsm/fsm_3_tb.v

`timescale 1ns/1ps  //时间精度
`define    Clock 20 //时钟周期

module FSM_3_tb;
//--------------------< 端口 >------------------------------------------
reg                     clk                 ;
reg                     rst_n               ;
reg  [1:0]              in                  ;
wire [1:0]              out                 ;
wire                    out_vld             ;

//----------------------------------------------------------------------
//--   模块例化
//----------------------------------------------------------------------
FSM_3 u_FSM_3
(
    .clk                (clk                ),
    .rst_n              (rst_n              ),
    .in                 (in                 ),
    .out                (out                ),
    .out_vld            (out_vld            )
);

//----------------------------------------------------------------------
//--   状态机名称查看器
//----------------------------------------------------------------------
localparam S0           = 4'b0001           ;
localparam S1           = 4'b0010           ;
localparam S2           = 4'b0100           ;
localparam S3           = 4'b1000           ;
//2字符16位
reg [15:0]              state_name          ;

always@(*)begin
    case(u_FSM_3.state_c)
        S0:     state_name = "S0";
        S1:     state_name = "S1";
        S2:     state_name = "S2";
        S3:     state_name = "S3";
        default:state_name = "S0";
    endcase
end

//----------------------------------------------------------------------
//--   时钟信号和复位信号
//----------------------------------------------------------------------
initial begin
    clk = 1;
    forever
    #(`Clock/2) clk = ~clk;
end

initial begin
    rst_n = 0; #(`Clock*20+1);
    rst_n = 1;
end

//----------------------------------------------------------------------
//--   设计输入信号
//----------------------------------------------------------------------
initial begin

    $dumpfile("test.vcd");
    $dumpvars(0,FSM_3_tb);
    #1;
    in = 0;
    #(`Clock*20+1); //初始化完成
//情况1--------------------------
    in = 1;         //1块钱
    #(`Clock*1);
    in = 0;
    #(`Clock*1);
    in = 1;         //1块钱
    #(`Clock*1);
    in = 0;
    #(`Clock*1);
    in = 1;         //1块钱
    #(`Clock*1);
    in = 0;
    #(`Clock*1);
    in = 1;         //1块钱
    #(`Clock*1);
    in = 0;
    #(`Clock*10);
//情况2--------------------------
    in = 1;         //1块钱
    #(`Clock*1);
    in = 0;
    #(`Clock*1);
    in = 1;         //1块钱
    #(`Clock*1);
    in = 0;
    #(`Clock*1);
    in = 1;         //1块钱
    #(`Clock*1);
    in = 0;
    #(`Clock*1);
    in = 2;         //2块钱
    #(`Clock*1);
    in = 0;
    #(`Clock*10);
//情况3--------------------------
    in = 1;         //1块钱
    #(`Clock*1);
    in = 0;
    #(`Clock*1);
    in = 1;         //1块钱
    #(`Clock*1);
    in = 0;
    #(`Clock*1);
    in = 2;         //2块钱
    #(`Clock*1);
    in = 0;
    #(`Clock*10);
//情况4--------------------------
    in = 1;         //1块钱
    #(`Clock*1);
    in = 0;
    #(`Clock*1);
    in = 2;         //2块钱
    #(`Clock*1);
    in = 0;
    #(`Clock*1);
    in = 2;         //2块钱
    #(`Clock*1);
    in = 0;
    #(`Clock*10);
//情况5--------------------------
    in = 2;         //2块钱
    #(`Clock*1);
    in = 0;
    #(`Clock*1);
    in = 2;         //2块钱
    #(`Clock*1);
    in = 0;
    #(`Clock*10);


    $stop;
end


endmodule

code/exp2/fsm/test.vcd
$date
	Tue Nov  5 22:34:57 2024
$end

$version
	Synopsys VCS version S-2021.09-SP2_Full64
$end

$timescale
	1ps
$end

$comment Csum: 1 0721e0ff01d63865 $end


$scope module FSM_3_tb $end
$var reg 1 ! clk $end
$var reg 1 " rst_n $end
$var reg 2 # in [1:0] $end
$var wire 2 $ out [1:0] $end
$var wire 1 % out_vld $end
$var reg 16 & state_name [15:0] $end

$scope module u_FSM_3 $end
$var reg 4 ' state_c [3:0] $end
$var wire 1 ( clk $end
$var wire 1 ) rst_n $end
$var wire 2 * in [1:0] $end
$var reg 2 + out [1:0] $end
$var reg 1 , out_vld $end
$var reg 4 - state_n [3:0] $end
$upscope $end

$upscope $end

$enddefinitions $end

#0
$dumpvars
1!
0%
0"
0,
0)
bxx #
b00 $
b0001 '
b0001 -
b0101001100110000 &
bxx *
b00 +
1(
$end
#1000
b00 #
b00 *
#10000
0!
0(
#20000
1!
1(
#30000
0!
0(
#40000
1!
1(
#50000
0!
0(
#60000
1!
1(
#70000
0!
0(
#80000
1!
1(
#90000
0!
0(
#100000
1!
1(
#110000
0!
0(
#120000
1!
1(
#130000
0!
0(
#140000
1!
1(
#150000
0!
0(
#160000
1!
1(
#170000
0!
0(
#180000
1!
1(
#190000
0!
0(
#200000
1!
1(
#210000
0!
0(
#220000
1!
1(
#230000
0!
0(
#240000
1!
1(
#250000
0!
0(
#260000
1!
1(
#270000
0!
0(
#280000
1!
1(
#290000
0!
0(
#300000
1!
1(
#310000
0!
0(
#320000
1!
1(
#330000
0!
0(
#340000
1!
1(
#350000
0!
0(
#360000
1!
1(
#370000
0!
0(
#380000
1!
1(
#390000
0!
0(
#400000
1!
1(
#401000
1"
1)
#402000
b01 #
b01 *
b0010 -
#410000
0!
0(
#420000
1!
1(
b0010 '
b0101001100110001 &
b0100 -
#422000
b00 #
b00 *
b0010 -
#430000
0!
0(
#440000
1!
1(
#442000
b01 #
b01 *
b0100 -
#450000
0!
0(
#460000
1!
1(
b0100 '
b0101001100110010 &
b1000 -
#462000
b00 #
b00 *
b0100 -
#470000
0!
0(
#480000
1!
1(
#482000
b01 #
b01 *
b1000 -
#490000
0!
0(
#500000
1!
1(
b1000 '
b0101001100110011 &
b0001 -
#502000
b00 #
b00 *
b1000 -
#510000
0!
0(
#520000
1!
1(
#522000
b01 #
b01 *
b0001 -
#530000
0!
0(
#540000
1!
1(
1,
1%
b0001 '
b0101001100110000 &
b0010 -
#542000
b00 #
b00 *
b0001 -
#550000
0!
0(
#560000
1!
1(
0,
0%
#570000
0!
0(
#580000
1!
1(
#590000
0!
0(
#600000
1!
1(
#610000
0!
0(
#620000
1!
1(
#630000
0!
0(
#640000
1!
1(
#650000
0!
0(
#660000
1!
1(
#670000
0!
0(
#680000
1!
1(
#690000
0!
0(
#700000
1!
1(
#710000
0!
0(
#720000
1!
1(
#730000
0!
0(
#740000
1!
1(
#742000
b01 #
b01 *
b0010 -
#750000
0!
0(
#760000
1!
1(
b0010 '
b0101001100110001 &
b0100 -
#762000
b00 #
b00 *
b0010 -
#770000
0!
0(
#780000
1!
1(
#782000
b01 #
b01 *
b0100 -
#790000
0!
0(
#800000
1!
1(
b0100 '
b0101001100110010 &
b1000 -
#802000
b00 #
b00 *
b0100 -
#810000
0!
0(
#820000
1!
1(
#822000
b01 #
b01 *
b1000 -
#830000
0!
0(
#840000
1!
1(
b1000 '
b0101001100110011 &
b0001 -
#842000
b00 #
b00 *
b1000 -
#850000
0!
0(
#860000
1!
1(
#862000
b10 #
b10 *
b0001 -
#870000
0!
0(
#880000
1!
1(
b01 +
b01 $
1,
1%
b0001 '
b0101001100110000 &
b0100 -
#882000
b00 #
b00 *
b0001 -
#890000
0!
0(
#900000
1!
1(
b00 +
b00 $
0,
0%
#910000
0!
0(
#920000
1!
1(
#930000
0!
0(
#940000
1!
1(
#950000
0!
0(
#960000
1!
1(
#970000
0!
0(
#980000
1!
1(
#990000
0!
0(
#1000000
1!
1(
#1010000
0!
0(
#1020000
1!
1(
#1030000
0!
0(
#1040000
1!
1(
#1050000
0!
0(
#1060000
1!
1(
#1070000
0!
0(
#1080000
1!
1(
#1082000
b01 #
b01 *
b0010 -
#1090000
0!
0(
#1100000
1!
1(
b0010 '
b0101001100110001 &
b0100 -
#1102000
b00 #
b00 *
b0010 -
#1110000
0!
0(
#1120000
1!
1(
#1122000
b01 #
b01 *
b0100 -
#1130000
0!
0(
#1140000
1!
1(
b0100 '
b0101001100110010 &
b1000 -
#1142000
b00 #
b00 *
b0100 -
#1150000
0!
0(
#1160000
1!
1(
#1162000
b10 #
b10 *
b0001 -
#1170000
0!
0(
#1180000
1!
1(
1,
1%
b0001 '
b0101001100110000 &
b0100 -
#1182000
b00 #
b00 *
b0001 -
#1190000
0!
0(
#1200000
1!
1(
0,
0%
#1210000
0!
0(
#1220000
1!
1(
#1230000
0!
0(
#1240000
1!
1(
#1250000
0!
0(
#1260000
1!
1(
#1270000
0!
0(
#1280000
1!
1(
#1290000
0!
0(
#1300000
1!
1(
#1310000
0!
0(
#1320000
1!
1(
#1330000
0!
0(
#1340000
1!
1(
#1350000
0!
0(
#1360000
1!
1(
#1370000
0!
0(
#1380000
1!
1(
#1382000
b01 #
b01 *
b0010 -
#1390000
0!
0(
#1400000
1!
1(
b0010 '
b0101001100110001 &
b0100 -
#1402000
b00 #
b00 *
b0010 -
#1410000
0!
0(
#1420000
1!
1(
#1422000
b10 #
b10 *
b1000 -
#1430000
0!
0(
#1440000
1!
1(
b1000 '
b0101001100110011 &
b0001 -
#1442000
b00 #
b00 *
b1000 -
#1450000
0!
0(
#1460000
1!
1(
#1462000
b10 #
b10 *
b0001 -
#1470000
0!
0(
#1480000
1!
1(
b01 +
b01 $
1,
1%
b0001 '
b0101001100110000 &
b0100 -
#1482000
b00 #
b00 *
b0001 -
#1490000
0!
0(
#1500000
1!
1(
b00 +
b00 $
0,
0%
#1510000
0!
0(
#1520000
1!
1(
#1530000
0!
0(
#1540000
1!
1(
#1550000
0!
0(
#1560000
1!
1(
#1570000
0!
0(
#1580000
1!
1(
#1590000
0!
0(
#1600000
1!
1(
#1610000
0!
0(
#1620000
1!
1(
#1630000
0!
0(
#1640000
1!
1(
#1650000
0!
0(
#1660000
1!
1(
#1670000
0!
0(
#1680000
1!
1(
#1682000
b10 #
b10 *
b0100 -
#1690000
0!
0(
#1700000
1!
1(
b0100 '
b0101001100110010 &
b0001 -
#1702000
b00 #
b00 *
b0100 -
#1710000
0!
0(
#1720000
1!
1(
#1722000
b10 #
b10 *
b0001 -
#1730000
0!
0(
#1740000
1!
1(
1,
1%
b0001 '
b0101001100110000 &
b0100 -
#1742000
b00 #
b00 *
b0001 -
#1750000
0!
0(
#1760000
1!
1(
0,
0%
